Multicycle/Testbenches/Controller/aludec.v
module aludec(
    input [5:0] funct,
    input [1:0] aluop,
    output reg [2:0] alucontrol
);

    always @( * )
        case(aluop)
            3'b000: alucontrol <= 3'b010; // add
            3'b001: alucontrol <= 3'b010; // sub

            // RTYPE instruction use the 6-bit funct field of instruction to specify ALU operation
            3'b010: case(funct)
                6'b100000: alucontrol <= 3'b010; // ADD
                6'b100010: alucontrol <= 3'b110; // SUB
                6'b100100: alucontrol <= 3'b000; // AND
                6'b100101: alucontrol <= 3'b001; // OR
                6'b101010: alucontrol <= 3'b111; // SLT
                default: alucontrol <= 3'bxxx; // ???
            endcase
    default: alucontrol <= 3'bxxx; // ???
    endcase
endmodule

Multicycle/Testbenches/Controller/maindec.v
module maindec(
    input clk, reset,
    input [5:0] op,
    output pcwrite, memwrite, irwrite, regwrite,
    output alusrca, branch, iord, memtoreg, regdst,
    output [1:0] alusrcb,
    output [1:0] pcsrc,
    output [1:0] aluop
);

    // FSM States
    parameter FETCH = 5'b00000; // State 0
    parameter DECODE = 5'b00001; // State 1
    parameter MEMADR = 5'b00010; // State 2
    parameter MEMRD = 5'b00011; // State 3
    parameter MEMWB = 5'b00100; // State 4
    parameter MEMWR = 5'b00101; // State 5
    parameter EXECUTE = 5'b00110; // State 6
    parameter ALUWRITEBACK = 5'b00111; // State 7
    parameter BRANCH = 5'b01000; // State 8
    parameter ADDIEXECUTE = 5'b01001; // State 9
    parameter ADDIWRITEBACK = 5'b01010; // state a
    parameter JUMP = 5'b01011; // State b

    // MIPS Instruction Opcodes
    parameter LW = 6'b100011; // load word lw
    parameter SW = 6'b101011; // store word sw
    parameter RTYPE = 6'b000000; // R-type
    parameter BEQ = 6'b000100; // branch if equal beq
    parameter ADDI = 6'b001000; // add immediate addi
    parameter J = 6'b000010; // jump j
    reg [4:0] state, nextstate;
    reg [16:0] controls; 

    // state register
    always @(posedge clk or posedge reset)
        if(reset) 
            state <= FETCH;
        else 
            state <= nextstate;
                
    // next state logic
    always @( * )
        case(state)
            FETCH: nextstate <= DECODE;

            DECODE: case(op)
                LW: nextstate <= MEMADR;
                SW: nextstate <= MEMADR;
                RTYPE: nextstate <= EXECUTE;
                BEQ: nextstate <= BRANCH;
                ADDI: nextstate <= ADDIEXECUTE;
                J: nextstate <= JUMP;
                default: nextstate <= FETCH; // should never happen
                endcase

            MEMADR: case(op)
                    LW: nextstate <= MEMRD;
                    SW: nextstate <= MEMWR;
                    default: nextstate <= FETCH; // should never happen
                    endcase

            MEMRD: nextstate <= MEMWB;
            MEMWB: nextstate <= FETCH;
            MEMWR: nextstate <= FETCH;
            EXECUTE: nextstate <= ALUWRITEBACK;
            ALUWRITEBACK: nextstate <= FETCH;
            BRANCH: nextstate <= FETCH;
            ADDIEXECUTE: nextstate <= ADDIWRITEBACK;
            ADDIWRITEBACK: nextstate <= FETCH;
            JUMP: nextstate <= FETCH;

            default: nextstate <= FETCH; // should never happen
        endcase

    // output logic
    assign {pcwrite, memwrite, irwrite, regwrite, alusrca, branch, iord, memtoreg, regdst, alusrcb, pcsrc, aluop} = controls; 
    always @( * )
        case(state)
            FETCH: controls <= 19'b1010_00000_0100_00;
            DECODE: controls <= 19'b0000_00000_1100_00;
            MEMADR: controls <= 19'b0000_10000_1000_00;
            MEMRD: controls <= 19'b0000_00100_0000_00;
            MEMWB: controls <= 19'b0001_00010_0000_00;
            MEMWR: controls <= 19'b0100_00100_0000_00;
            EXECUTE: controls <= 19'b0000_10000_0000_10;
            ALUWRITEBACK: controls <= 19'b0001_00001_0000_00;
            BRANCH: controls <= 19'b0000_11000_0001_01;
            ADDIEXECUTE: controls <= 19'b0000_10000_1000_00;
            ADDIWRITEBACK: controls <= 19'b0001_00000_0000_00;
            JUMP: controls <= 19'b1000_00000_0010_00;
            default: controls <= 19'b0000_xxxxx_xxxx_xx; // should never happen
        endcase
endmodule

Multicycle/Testbenches/Pipeline/controller.v
module controller(
    input clk, reset,
    input [5:0] op, funct,
    input zero,
    output pcen, memwrite, irwrite, regwrite,
    output alusrca, iord, memtoreg, regdst,
    output [1:0] alusrcb,
    output [1:0] pcsrc,
    output [2:0] alucontrol
);

    wire [1:0] aluop;
    wire branch, pcwrite;

    // Main Decoder and ALU Decoder subunits.
    maindec md(clk, reset, op,
    pcwrite, memwrite, irwrite, regwrite,
    alusrca, branch, iord, memtoreg, regdst,
    alusrcb, pcsrc, aluop);
    aludec ad(funct, aluop, alucontrol);
    assign pcen = pcwrite | (branch & zero);
endmodule

Multicycle/Testbenches/ControlUnit/controller_tb.v
module controller_tb;  
    reg clk, reset, zero;  
    reg [5:0] op, funct;  
    
    wire   iord, memwrite, irwrite, regdst, memtoreg, regwrite, alusrca, pcen;  
    wire [1:0] alusrcb, pcsrc;  
    wire [2:0] alucontrol;  
    
    reg [31:0] instr;  
    
    always @ ( * )  
    begin  
        op <= instr [31:26];  
        funct <= instr [5:0];  
    end  
    
    controller uut(clk, reset, op, funct, zero, pcen, memwrite, irwrite, regwrite, alusrca, iord, memtoreg, regdst, alusrcb, pcsrc, alucontrol);  
    
    always #1 clk = ~clk;  
    
    initial begin  
        $dumpfile("controller_tb.vcd");  
        $dumpvars(0, controller_tb);

        clk = 0;  
        reset = 1;  
        zero = 0;  
        
        #2  reset = 1; instr = 0;  
        #2  reset = 0; instr = 32'h20020005; //addi  
        #2  reset = 0; instr = 32'h20020005; //addi  
        
        #2  reset = 0; instr = 32'h20020005; //addi  
        #2 reset = 0; instr = 32'h20020005; //addi  
        #2 reset = 0; instr = 32'h2003000c; //addi  
        #2 reset = 0; instr = 32'h2003000c; //addi  
        #2 reset = 0; instr = 32'h2003000c; //addi  
        #2 reset = 0; instr = 32'h00e22025; //or  
        #2 reset = 0; instr = 32'h00e22025; //or  
        #2 reset = 0; instr = 32'h00e22025; //or  
        #2 reset = 0; instr = 32'h00e22025; //or  
        #2 reset = 0; instr = 32'h00642824; //and  
        #2 reset = 0; instr = 32'h00642824; //and  
        #2 reset = 0; instr = 32'h00642824; //and  
        #2 reset = 0; instr = 32'h00642824; //and  
        #2 reset = 0; instr = 32'h00a42820; //add  
        #2 reset = 0; instr = 32'h00a42820; //add  
        #2 reset = 0; instr = 32'h00a42820; //add  
        #2 reset = 0; instr = 32'h00a42820; //add  
        #2 reset = 0; instr = 32'h00853820; //add  
        #2 reset = 0; instr = 32'h00853820; //add  
        #2 reset = 0; instr = 32'h00853820; //add  
        #2 reset = 0; instr = 32'h00853820; //add  
        #2 reset = 0; instr = 32'h00e23822; //sub  
        #2 reset = 0; instr = 32'h00e23822; //sub  
        #2 reset = 0; instr = 32'h00e23822; //sub  
        #2 reset = 0; instr = 32'h00e23822; //sub  
        #2 reset = 0; instr = 32'hac670044; //sw  
        #2 reset = 0; instr = 32'hac670044; //sw  
        #2 reset = 0; instr = 32'hac670044; //sw  
        #2 reset = 0; instr = 32'hac670044; //sw  
        #2 reset = 0; instr = 32'h8c020050; //lw  
        #2 reset = 0; instr = 32'h8c020050; //lw  
        #2 reset = 0; instr = 32'h8c020050; //lw  
        #2 reset = 0; instr = 32'h8c020050; //lw  
        #2 reset = 0; instr = 32'h8c020050; //lw  
        #2 $finish;  
    end  
endmodule

Multicycle/Testbenches/Controller/controller_tb.vcd
$date
	Sat Aug 31 23:05:35 2024
$end
$version
	Icarus Verilog
$end
$timescale
	1s
$end
$scope module controller_tb $end
$var wire 1 ! regwrite $end
$var wire 1 " regdst $end
$var wire 2 # pcsrc [1:0] $end
$var wire 1 $ pcen $end
$var wire 1 % memwrite $end
$var wire 1 & memtoreg $end
$var wire 1 ' irwrite $end
$var wire 1 ( iord $end
$var wire 2 ) alusrcb [1:0] $end
$var wire 1 * alusrca $end
$var wire 3 + alucontrol [2:0] $end
$var reg 1 , clk $end
$var reg 6 - funct [5:0] $end
$var reg 32 . instr [31:0] $end
$var reg 6 / op [5:0] $end
$var reg 1 0 reset $end
$var reg 1 1 zero $end
$scope module uut $end
$var wire 1 , clk $end
$var wire 6 2 funct [5:0] $end
$var wire 6 3 op [5:0] $end
$var wire 1 $ pcen $end
$var wire 1 0 reset $end
$var wire 1 1 zero $end
$var wire 1 ! regwrite $end
$var wire 1 " regdst $end
$var wire 1 4 pcwrite $end
$var wire 2 5 pcsrc [1:0] $end
$var wire 1 % memwrite $end
$var wire 1 & memtoreg $end
$var wire 1 ' irwrite $end
$var wire 1 ( iord $end
$var wire 1 6 branch $end
$var wire 2 7 alusrcb [1:0] $end
$var wire 1 * alusrca $end
$var wire 2 8 aluop [1:0] $end
$var wire 3 9 alucontrol [2:0] $end
$scope module ad $end
$var wire 6 : funct [5:0] $end
$var wire 2 ; aluop [1:0] $end
$var reg 3 < alucontrol [2:0] $end
$upscope $end
$scope module md $end
$var wire 1 , clk $end
$var wire 6 = op [5:0] $end
$var wire 1 0 reset $end
$var wire 1 ! regwrite $end
$var wire 1 " regdst $end
$var wire 1 4 pcwrite $end
$var wire 2 > pcsrc [1:0] $end
$var wire 1 % memwrite $end
$var wire 1 & memtoreg $end
$var wire 1 ' irwrite $end
$var wire 1 ( iord $end
$var wire 1 6 branch $end
$var wire 2 ? alusrcb [1:0] $end
$var wire 1 * alusrca $end
$var wire 2 @ aluop [1:0] $end
$var parameter 6 A ADDI $end
$var parameter 5 B ADDIEXECUTE $end
$var parameter 5 C ADDIWRITEBACK $end
$var parameter 5 D ALUWRITEBACK $end
$var parameter 6 E BEQ $end
$var parameter 5 F BRANCH $end
$var parameter 5 G DECODE $end
$var parameter 5 H EXECUTE $end
$var parameter 5 I FETCH $end
$var parameter 6 J J $end
$var parameter 5 K JUMP $end
$var parameter 6 L LW $end
$var parameter 5 M MEMADR $end
$var parameter 5 N MEMRD $end
$var parameter 5 O MEMWB $end
$var parameter 5 P MEMWR $end
$var parameter 6 Q RTYPE $end
$var parameter 6 R SW $end
$var reg 17 S controls [16:0] $end
$var reg 5 T nextstate [4:0] $end
$var reg 5 U state [4:0] $end
$upscope $end
$upscope $end
$upscope $end
$enddefinitions $end
$comment Show the parameter values. $end
$dumpall
b101011 R
b0 Q
b101 P
b100 O
b11 N
b10 M
b100011 L
b1011 K
b10 J
b0 I
b110 H
b1 G
b1000 F
b100 E
b111 D
b1010 C
b1001 B
b1000 A
$end
#0
$dumpvars
b0 U
b1 T
b101000000010000 S
b0 @
b1 ?
b0 >
bx =
b10 <
b0 ;
bx :
b10 9
b0 8
b1 7
06
b0 5
14
bx 3
bx 2
01
10
bx /
bx .
bx -
0,
b10 +
0*
b1 )
0(
1'
0&
0%
1$
b0 #
0"
0!
$end
#1
1,
#2
b0 -
b0 2
b0 :
b0 /
b0 3
b0 =
0,
b0 .
#3
1,
#4
b101 -
b101 2
b101 :
b1000 /
b1000 3
b1000 =
0,
b100000000000100000000000000101 .
00
#5
0$
b11 )
b11 7
b11 ?
0'
04
b110000 S
b1001 T
b1 U
1,
#6
0,
#7
b10 )
b10 7
b10 ?
1*
b10000100000 S
b1010 T
b1001 U
1,
#8
0,
#9
b0 )
b0 7
b0 ?
0*
1!
b100000000000 S
b0 T
b1010 U
1,
#10
0,
#11
1$
b1 )
b1 7
b1 ?
0!
1'
14
b101000000010000 S
b1 T
b0 U
1,
#12
b1100 -
b1100 2
b1100 :
0,
b100000000000110000000000001100 .
#13
0$
b11 )
b11 7
b11 ?
0'
04
b110000 S
b1001 T
b1 U
1,
#14
0,
#15
b10 )
b10 7
b10 ?
1*
b10000100000 S
b1010 T
b1001 U
1,
#16
0,
#17
b0 )
b0 7
b0 ?
0*
1!
b100000000000 S
b0 T
b1010 U
1,
#18
b100101 -
b100101 2
b100101 :
b0 /
b0 3
b0 =
0,
b111000100010000000100101 .
#19
1$
b1 )
b1 7
b1 ?
0!
1'
14
b101000000010000 S
b1 T
b0 U
1,
#20
0,
#21
0$
b11 )
b11 7
b11 ?
0'
04
b110000 S
b110 T
b1 U
1,
#22
0,
#23
b1 +
b1 9
b1 <
b10 8
b10 ;
b10 @
b0 )
b0 7
b0 ?
1*
b10000000010 S
b111 T
b110 U
1,
#24
0,
#25
b10 +
b10 9
b10 <
b0 8
b0 ;
b0 @
1"
0*
1!
b100001000000 S
b0 T
b111 U
1,
#26
b100100 -
b100100 2
b100100 :
0,
b11001000010100000100100 .
#27
1$
b1 )
b1 7
b1 ?
0"
0!
1'
14
b101000000010000 S
b1 T
b0 U
1,
#28
0,
#29
0$
b11 )
b11 7
b11 ?
0'
04
b110000 S
b110 T
b1 U
1,
#30
0,
#31
b0 +
b0 9
b0 <
b10 8
b10 ;
b10 @
b0 )
b0 7
b0 ?
1*
b10000000010 S
b111 T
b110 U
1,
#32
0,
#33
b10 +
b10 9
b10 <
b0 8
b0 ;
b0 @
1"
0*
1!
b100001000000 S
b0 T
b111 U
1,
#34
b100000 -
b100000 2
b100000 :
0,
b101001000010100000100000 .
#35
1$
b1 )
b1 7
b1 ?
0"
0!
1'
14
b101000000010000 S
b1 T
b0 U
1,
#36
0,
#37
0$
b11 )
b11 7
b11 ?
0'
04
b110000 S
b110 T
b1 U
1,
#38
0,
#39
b10 8
b10 ;
b10 @
b0 )
b0 7
b0 ?
1*
b10000000010 S
b111 T
b110 U
1,
#40
0,
#41
b0 8
b0 ;
b0 @
1"
0*
1!
b100001000000 S
b0 T
b111 U
1,
#42
0,
b100001010011100000100000 .
#43
1$
b1 )
b1 7
b1 ?
0"
0!
1'
14
b101000000010000 S
b1 T
b0 U
1,
#44
0,
#45
0$
b11 )
b11 7
b11 ?
0'
04
b110000 S
b110 T
b1 U
1,
#46
0,
#47
b10 8
b10 ;
b10 @
b0 )
b0 7
b0 ?
1*
b10000000010 S
b111 T
b110 U
1,
#48
0,
#49
b0 8
b0 ;
b0 @
1"
0*
1!
b100001000000 S
b0 T
b111 U
1,
#50
b100010 -
b100010 2
b100010 :
0,
b111000100011100000100010 .
#51
1$
b1 )
b1 7
b1 ?
0"
0!
1'
14
b101000000010000 S
b1 T
b0 U
1,
#52
0,
#53
0$
b11 )
b11 7
b11 ?
0'
04
b110000 S
b110 T
b1 U
1,
#54
0,
#55
b110 +
b110 9
b110 <
b10 8
b10 ;
b10 @
b0 )
b0 7
b0 ?
1*
b10000000010 S
b111 T
b110 U
1,
#56
0,
#57
b10 +
b10 9
b10 <
b0 8
b0 ;
b0 @
1"
0*
1!
b100001000000 S
b0 T
b111 U
1,
#58
b100 -
b100 2
b100 :
b101011 /
b101011 3
b101011 =
0,
b10101100011001110000000001000100 .
#59
1$
b1 )
b1 7
b1 ?
0"
0!
1'
14
b101000000010000 S
b1 T
b0 U
1,
#60
0,
#61
0$
b11 )
b11 7
b11 ?
0'
04
b110000 S
b10 T
b1 U
1,
#62
0,
#63
b10 )
b10 7
b10 ?
1*
b10000100000 S
b101 T
b10 U
1,
#64
0,
#65
b0 )
b0 7
b0 ?
1(
0*
1%
b10000100000000 S
b0 T
b101 U
1,
#66
b10000 -
b10000 2
b10000 :
b100011 /
b100011 3
b100011 =
0,
b10001100000000100000000001010000 .
#67
1$
b1 )
b1 7
b1 ?
0(
1'
0%
14
b101000000010000 S
b1 T
b0 U
1,
#68
0,
#69
0$
b11 )
b11 7
b11 ?
0'
04
b110000 S
b10 T
b1 U
1,
#70
0,
#71
b10 )
b10 7
b10 ?
1*
b10000100000 S
b11 T
b10 U
1,
#72
0,
#73
b0 )
b0 7
b0 ?
1(
0*
b100000000 S
b100 T
b11 U
1,
#74
0,
#75
1&
0(
1!
b100010000000 S
b0 T
b100 U
1,
